setup.py
xing/__init__.py
xing/logger.py
xing/xachartdata.py
xing/xacom.py
xing/xaquery.py
xing/xareal.py
xing/xasession.py
xing/res/B7_.res
xing/res/B7__1.res
xing/res/BMT.res
xing/res/BMT_1.res
xing/res/BM_.res
xing/res/BM__1.res
xing/res/C01.res
xing/res/C01_1.res
xing/res/CCEAQ01100.res
xing/res/CCEAQ01100_1.res
xing/res/CCEAQ06000.res
xing/res/CCEAQ06000_1.res
xing/res/CCEAQ10100.res
xing/res/CCEAQ10100_1.res
xing/res/CCEAQ50600.res
xing/res/CCEAQ50600_1.res
xing/res/CCEAT00100.res
xing/res/CCEAT00100_1.res
xing/res/CCEAT00200.res
xing/res/CCEAT00200_1.res
xing/res/CCEAT00300.res
xing/res/CCEAT00300_1.res
xing/res/CCEBQ10500.res
xing/res/CCEBQ10500_1.res
xing/res/CD0.res
xing/res/CD0_1.res
xing/res/CDPCQ04700.res
xing/res/CDPCQ04700_1.res
xing/res/CEXAQ21100.res
xing/res/CEXAQ21100_1.res
xing/res/CEXAQ21200.res
xing/res/CEXAQ21200_1.res
xing/res/CEXAQ31100.res
xing/res/CEXAQ31100_1.res
xing/res/CEXAQ31200.res
xing/res/CEXAQ31200_1.res
xing/res/CEXAT11100.res
xing/res/CEXAT11100_1.res
xing/res/CEXAT11200.res
xing/res/CEXAT11200_1.res
xing/res/CEXAT11300.res
xing/res/CEXAT11300_1.res
xing/res/CFOAQ00600.res
xing/res/CFOAQ00600_1.res
xing/res/CFOAQ10100.res
xing/res/CFOAQ10100_1.res
xing/res/CFOAT00100.res
xing/res/CFOAT00100_1.res
xing/res/CFOAT00200.res
xing/res/CFOAT00200_1.res
xing/res/CFOAT00300.res
xing/res/CFOAT00300_1.res
xing/res/CFOBQ10500.res
xing/res/CFOBQ10500_1.res
xing/res/CFOBQ10800.res
xing/res/CFOBQ10800_1.res
xing/res/CFOEQ11100.res
xing/res/CFOEQ11100_1.res
xing/res/CFOEQ82600.res
xing/res/CFOEQ82600_1.res
xing/res/CFOFQ02400.res
xing/res/CFOFQ02400_1.res
xing/res/CLNAQ00100.res
xing/res/CLNAQ00100_1.res
xing/res/CM0.res
xing/res/CM0_1.res
xing/res/CM1.res
xing/res/CM1_1.res
xing/res/CM2.res
xing/res/CM2_1.res
xing/res/CSPAQ00600.res
xing/res/CSPAQ00600_1.res
xing/res/CSPAQ12200.res
xing/res/CSPAQ12200_1.res
xing/res/CSPAQ12300.res
xing/res/CSPAQ12300_1.res
xing/res/CSPAQ13700.res
xing/res/CSPAQ13700_1.res
xing/res/CSPAT00600.res
xing_plus.egg-info/PKG-INFO
xing_plus.egg-info/SOURCES.txt
xing_plus.egg-info/dependency_links.txt
xing_plus.egg-info/requires.txt
xing_plus.egg-info/top_level.txt