Metadata-Version: 1.1
Name: xing-plus
Version: 1.0.2
Summary: more easy eBEST INVESTMENT API
Home-page: https://github.com/sculove/xing-plus
Author: sculove
Author-email: sculove@gmail.com
License: MIT License
Keywords: xing,stock,systemtrading
Platform: UNKNOWN
Classifier: Environment :: Win32 (MS Windows)
Classifier: License :: OSI Approved :: MIT License
Classifier: Programming Language :: Python
Classifier: Programming Language :: Python :: 3.5
Classifier: Natural Language :: Korean
